shvcli_ell/__init__.py
shvcli_ell/__version__.py
shvcli_ell/plugin.py
shvcli_ell/py.typed
shvcli_ell/timesync.py
shvcli_ell/timezone.py
shvcli_ell-0.1.0.dist-info/METADATA
shvcli_ell-0.1.0.dist-info/WHEEL
shvcli_ell-0.1.0.dist-info/entry_points.txt
shvcli_ell-0.1.0.dist-info/top_level.txt
shvcli_ell-0.1.0.dist-info/RECORD
